poetry_homebrew_formula/__init__.py
poetry_homebrew_formula/exceptions.py
poetry_homebrew_formula/plugin.py
poetry_homebrew_formula/templates/formula.rb.j2
poetry_homebrew_formula/templates/package_url.rb.j2
poetry_homebrew_formula/templates/resources.rb.j2
poetry_homebrew_formula/templating.py
poetry_homebrew_formula/types.py
poetry_homebrew_formula-0.3.0.dist-info/LICENSE
poetry_homebrew_formula-0.3.0.dist-info/METADATA
poetry_homebrew_formula-0.3.0.dist-info/WHEEL
poetry_homebrew_formula-0.3.0.dist-info/entry_points.txt
poetry_homebrew_formula-0.3.0.dist-info/RECORD
