Metadata-Version: 2.1
Name: poetry-homebrew-formula
Version: 0.3.0
Summary: Generate Homebrew formulae for Poetry projects
Home-page: https://github.com/janw/poetry-homebrew-formula
License: MIT
Author: Jan Willhaus
Author-email: mail@janwillhaus.de
Maintainer: Jan Willhaus
Maintainer-email: mail@janwillhaus.de
Requires-Python: >=3.10,<4.0
Classifier: License :: OSI Approved :: MIT License
Classifier: Programming Language :: Python :: 3
Classifier: Programming Language :: Python :: 3.10
Classifier: Programming Language :: Python :: 3.11
Classifier: Programming Language :: Python :: 3.12
Requires-Dist: jinja2 (>=3.1.2,<4.0.0)
Requires-Dist: poetry (>=1.7,<2.0)
Project-URL: Repository, https://github.com/janw/poetry-homebrew-formula
